makinyan/__init__.py
makinyan/analyzer/__init__.py
makinyan/analyzer/display.py
makinyan/analyzer/nlang.py
makinyan/dget/__init__.py
makinyan/dget/s3.py
makinyan/optimizer/__init__.py
makinyan/tools/__init__.py
makinyan/tools/dget/__init__.py
makinyan/tools/dget/s3.py
makinyan/tools/dtransform/__init__.py
makinyan/tools/dtransform/matrix.py
makinyan/tools/file/__init__.py
makinyan/tools/file/dfile_loader.py
makinyan-0.0.29.dist-info/METADATA
makinyan-0.0.29.dist-info/WHEEL
makinyan-0.0.29.dist-info/entry_points.txt
makinyan-0.0.29.dist-info/top_level.txt
makinyan-0.0.29.dist-info/RECORD
